informaticsmatters/protobuf/__init__.py
informaticsmatters/protobuf/accountserver/__init__.py
informaticsmatters/protobuf/accountserver/merchant_authority_request_response_message_pb2.py
informaticsmatters/protobuf/accountserver/merchant_processing_charge_message_pb2.py
informaticsmatters/protobuf/accountserver/merchant_storage_charge_message_pb2.py
informaticsmatters/protobuf/common/__init__.py
informaticsmatters/protobuf/common/alert_message_pb2.py
informaticsmatters/protobuf/datamanager/__init__.py
informaticsmatters/protobuf/datamanager/cultivate_message_pb2.py
informaticsmatters/protobuf/datamanager/pod_event_message_pb2.py
informaticsmatters/protobuf/datamanager/pod_message_pb2.py
informaticsmatters/protobuf/datamanager/processing_cost_message_pb2.py
informaticsmatters/protobuf/datamanager/storage_bytes_message_pb2.py
informaticsmatters/protobuf/datamanager/workflow_message_pb2.py
im_protobuf-8.2.1.dist-info/LICENSE
im_protobuf-8.2.1.dist-info/METADATA
im_protobuf-8.2.1.dist-info/WHEEL
im_protobuf-8.2.1.dist-info/top_level.txt
im_protobuf-8.2.1.dist-info/RECORD
