Metadata-Version: 2.2
Name: im-protobuf
Version: 8.2.1
Summary: Cross-product protocol buffers
Home-page: https://github.com/informaticsmatters/squonk2-protobuf
Author: Alan Christie
Author-email: achristie@informaticsmatters.com
License: MIT
Keywords: protobuf protoc messaging
Platform: any
Classifier: Development Status :: 5 - Production/Stable
Classifier: Environment :: Other Environment
Classifier: Intended Audience :: Developers
Classifier: License :: OSI Approved :: MIT License
Classifier: Programming Language :: Python :: 3.11
Classifier: Topic :: Software Development :: Libraries :: Python Modules
Classifier: Operating System :: POSIX :: Linux
License-File: LICENSE
Requires-Dist: protobuf<7.0,>=6.30.1
Dynamic: author
Dynamic: author-email
Dynamic: classifier
Dynamic: description
Dynamic: description-content-type
Dynamic: home-page
Dynamic: keywords
Dynamic: license
Dynamic: platform
Dynamic: requires-dist
Dynamic: summary
